langchain_ai21/__init__.py
langchain_ai21/ai21_base.py
langchain_ai21/chat/__init__.py
langchain_ai21/chat/chat_adapter.py
langchain_ai21/chat/chat_factory.py
langchain_ai21/chat_models.py
langchain_ai21/contextual_answers.py
langchain_ai21/embeddings.py
langchain_ai21/llms.py
langchain_ai21/py.typed
langchain_ai21/semantic_text_splitter.py
gigachain_ai21-0.1.8.dist-info/LICENSE
gigachain_ai21-0.1.8.dist-info/METADATA
gigachain_ai21-0.1.8.dist-info/WHEEL
gigachain_ai21-0.1.8.dist-info/RECORD
